nrslib/__about__.py
nrslib/__init__.py
nrslib/configs/BERT.yaml
nrslib/configs/test.yaml
nrslib/configs/train.yaml
nrslib/configs/callbacks/default.yaml
nrslib/configs/callbacks/dkn.yaml
nrslib/configs/callbacks/naml.yaml
nrslib/configs/callbacks/none.yaml
nrslib/configs/callbacks/test.yaml
nrslib/configs/datamodule/mind.yaml
nrslib/configs/debug/default.yaml
nrslib/configs/debug/limit_batches.yaml
nrslib/configs/debug/overfit.yaml
nrslib/configs/debug/profiler.yaml
nrslib/configs/debug/step.yaml
nrslib/configs/debug/test_only.yaml
nrslib/configs/experiment/MKR.yaml
nrslib/configs/experiment/collaborativeFiltering.yaml
nrslib/configs/experiment/dkn.yaml
nrslib/configs/experiment/example.yaml
nrslib/configs/experiment/lstur.yaml
nrslib/configs/experiment/naml.yaml
nrslib/configs/experiment/nrms.yaml
nrslib/configs/experiment/rippleNet.yaml
nrslib/configs/hparams_search/mind_Collaborative_optuna.yaml
nrslib/configs/hparams_search/mind_MKR_optuna.yaml
nrslib/configs/hparams_search/mind_RippleNet_optuna.yaml
nrslib/configs/hparams_search/mnist_optuna.yaml
nrslib/configs/local/.gitkeep
nrslib/configs/log_dir/debug.yaml
nrslib/configs/log_dir/default.yaml
nrslib/configs/log_dir/evaluation.yaml
nrslib/configs/logger/comet.yaml
nrslib/configs/logger/csv.yaml
nrslib/configs/logger/many_loggers.yaml
nrslib/configs/logger/mlflow.yaml
nrslib/configs/logger/neptune.yaml
nrslib/configs/logger/tensorboard.yaml
nrslib/configs/logger/wandb.yaml
nrslib/configs/model/MKR.yaml
nrslib/configs/model/bert.yaml
nrslib/configs/model/collaborativeFiltering.yaml
nrslib/configs/model/dkn.yaml
nrslib/configs/model/lstur.yaml
nrslib/configs/model/mnist.yaml
nrslib/configs/model/naml.yaml
nrslib/configs/model/nrms.yaml
nrslib/configs/model/rippleNet.yaml
nrslib/configs/trainer/ddp.yaml
nrslib/configs/trainer/default.yaml
nrslib/configs/trainer/dkn.yaml
nrslib/configs/trainer/lstur.yaml
nrslib/configs/trainer/naml.yaml
nrslib/src/__init__.py
nrslib/src/testing_pipeline.py
nrslib-0.0.1.dist-info/METADATA
nrslib-0.0.1.dist-info/WHEEL
nrslib-0.0.1.dist-info/licenses/LICENSE
nrslib-0.0.1.dist-info/RECORD
