Metadata-Version: 2.1
Name: nrslib
Version: 0.0.1
Summary: Standardised Library for the Benchmarking of News Recommenders Systems
Project-URL: Documentation, https://newsrecommenderlib.github.io/
Project-URL: Issues, https://github.com/newsrecommenderlib/nrslib/issues
Project-URL: Source, https://github.com/newsrecommenderlib/nrslib
Author: Ahmed Elzamarany, Nadine Maeser, Noel Chia
License-File: LICENSE
Classifier: Development Status :: 4 - Beta
Classifier: Programming Language :: Python
Classifier: Programming Language :: Python :: 3.7
Classifier: Programming Language :: Python :: 3.8
Classifier: Programming Language :: Python :: 3.9
Classifier: Programming Language :: Python :: 3.10
Classifier: Programming Language :: Python :: 3.11
Classifier: Programming Language :: Python :: Implementation :: CPython
Classifier: Programming Language :: Python :: Implementation :: PyPy
Requires-Python: >=3.7
Requires-Dist: black
Requires-Dist: flake8
Requires-Dist: hydra-colorlog>=1.1.0
Requires-Dist: hydra-core>=1.1.0
Requires-Dist: hydra-optuna-sweeper>=1.1.0
Requires-Dist: isort
Requires-Dist: nbstripout
Requires-Dist: nltk
Requires-Dist: pandas
Requires-Dist: pre-commit
Requires-Dist: pudb
Requires-Dist: pytest
Requires-Dist: python-dotenv
Requires-Dist: pytorch-lightning>=1.5.10
Requires-Dist: retrying
Requires-Dist: rich
Requires-Dist: scikit-learn
Requires-Dist: swifter
Requires-Dist: tensorboard
Requires-Dist: torch>=1.10.0
Requires-Dist: torchmetrics>=0.7.0
Requires-Dist: torchvision>=0.11.0
